pyscreech/__init__.py
pyscreech/audio.py
pyscreech/cli.py
pyscreech/filter.py
pyscreech/score.py
pyscreech/stipa.py
pyscreech/stoi.py
pyscreech/wer.py
pyscreech-1.0.0.dist-info/METADATA
pyscreech-1.0.0.dist-info/WHEEL
pyscreech-1.0.0.dist-info/licenses/LICENSE
pyscreech-1.0.0.dist-info/RECORD
