Metadata-Version: 2.1
Name: pyscreech
Version: 1.0.0
Summary: PyScreech - Audio Performance Library
Project-URL: Source, https://github.com/hensh2ss/pyscreech
Project-URL: Documentation, https://github.com/hensh2ss/pyscreech
Author-email: Seth Henshaw <seth.s.henshaw@leidos.com>
License-File: LICENSE
Classifier: Development Status :: 3 - Alpha
Classifier: Environment :: Console
Classifier: Intended Audience :: Developers
Classifier: Intended Audience :: Education
Classifier: Intended Audience :: Science/Research
Classifier: License :: OSI Approved :: MIT License
Classifier: Natural Language :: English
Classifier: Programming Language :: Python :: 3.8
Classifier: Programming Language :: Python :: 3.9
Classifier: Programming Language :: Python :: 3.10
Classifier: Topic :: Multimedia :: Sound/Audio :: Analysis
Requires-Python: >=3.8
Requires-Dist: jiwer==3.0.3
Requires-Dist: librosa~=0.10.0.post2
Requires-Dist: loguru>=0.6.0
Requires-Dist: matplotlib~=3.7.2
Requires-Dist: numpy>=1.24.4
Requires-Dist: openai-whisper==20231117
Requires-Dist: pystoi~=0.3.3
Provides-Extra: developer
Requires-Dist: black[jupyter]==22.*; extra == 'developer'
Requires-Dist: coverage; extra == 'developer'
Requires-Dist: flake8; extra == 'developer'
Requires-Dist: hatch; extra == 'developer'
Requires-Dist: pip>=23.1.1; extra == 'developer'
Requires-Dist: pytest>=6.0.0; extra == 'developer'
Requires-Dist: setuptools; extra == 'developer'
Requires-Dist: twine; extra == 'developer'
Requires-Dist: wheel; extra == 'developer'
